solid/__init__.py
solid/auth.py
solid/solid_api.py
solid/utils/__init__.py
solid/utils/api_util.py
solid/utils/folder_utils.py
solid_file-0.2.1.dist-info/LICENSE
solid_file-0.2.1.dist-info/METADATA
solid_file-0.2.1.dist-info/WHEEL
solid_file-0.2.1.dist-info/top_level.txt
solid_file-0.2.1.dist-info/RECORD
