Metadata-Version: 2.1
Name: solid-file
Version: 0.2.1
Summary: Solid Python library (http://solidproject.org)
Home-page: https://github.com/twonote/solid-file-python
Author: hrchu
Author-email: petertc.chu@gmail.com
Project-URL: Bug Tracker, https://github.com/twonote/solid-file-python/issues
Classifier: Programming Language :: Python :: 3
Classifier: License :: OSI Approved :: MIT License
Classifier: Operating System :: OS Independent
Classifier: Topic :: System :: Systems Administration
Classifier: Topic :: Utilities
Requires-Python: >=3.7
License-File: LICENSE
Requires-Dist: httpx (==0.23.0)
Requires-Dist: rdflib (==5.0.0)
